<?xml version="1.0" encoding="utf-8" ?>
<dwsync>
<file name="catarog.jpg" server="18.179.138.137" local="132981767516681390" remote="132913353600000000" Dst="0" />
<file name="check.svg" server="18.179.138.137" local="132981767517762232" remote="132913353600000000" Dst="0" />
<file name="highway01.jpg" server="18.179.138.137" local="132981767517782109" remote="132913353600000000" Dst="0" />
<file name="highway02.jpg" server="18.179.138.137" local="132981767519509680" remote="132913353600000000" Dst="0" />
<file name="highway03.jpg" server="18.179.138.137" local="132981767519529630" remote="132913353600000000" Dst="0" />
<file name="highway_map.svg" server="18.179.138.137" local="132981767520598848" remote="132913353600000000" Dst="0" />
<file name="highway04.jpg" server="18.179.138.137" local="132981767520847144" remote="132913353600000000" Dst="0" />
<file name="interview02.jpg" server="18.179.138.137" local="132981767521336198" remote="132913353600000000" Dst="0" />
<file name="spot_01.jpg" server="18.179.138.137" local="132981767521923494" remote="132913353600000000" Dst="0" />
<file name="interview01.jpg" server="18.179.138.137" local="132981767521973076" remote="132913353600000000" Dst="0" />
<file name="spot_02.jpg" server="18.179.138.137" local="132981767522542719" remote="132913353600000000" Dst="0" />
<file name="spot_04.jpg" server="18.179.138.137" local="132981767523899493" remote="132913353600000000" Dst="0" />
<file name="map.jpg" server="18.179.138.137" local="132981767524019178" remote="132913353600000000" Dst="0" />
<file name="spot_03.jpg" server="18.179.138.137" local="132981767524198801" remote="132913353600000000" Dst="0" />
<file name="spot_05.jpg" server="18.179.138.137" local="132981767524489278" remote="132913353600000000" Dst="0" />
<file name="spot_06.jpg" server="18.179.138.137" local="132981767525721135" remote="132913353600000000" Dst="0" />
<file name="spot_08.jpg" server="18.179.138.137" local="132981767525781385" remote="132913353600000000" Dst="0" />
<file name="spot_07.jpg" server="18.179.138.137" local="132981767526595671" remote="132913353600000000" Dst="0" />
<file name="spot_10.jpg" server="18.179.138.137" local="132981767526615812" remote="132913353600000000" Dst="0" />
<file name="spot_11.jpg" server="18.179.138.137" local="132981767527414650" remote="132913353600000000" Dst="0" />
<file name="spot_09.jpg" server="18.179.138.137" local="132981767527547693" remote="132913353600000000" Dst="0" />
<file name="spot_13.jpg" server="18.179.138.137" local="132981767527977334" remote="132913353600000000" Dst="0" />
<file name="spot_12.jpg" server="18.179.138.137" local="132981767528894881" remote="132913353600000000" Dst="0" />
<file name="spot_15.jpg" server="18.179.138.137" local="132981767529104605" remote="132913353600000000" Dst="0" />
<file name="spot_14.jpg" server="18.179.138.137" local="132981767529713357" remote="132913353600000000" Dst="0" />
<file name="top_main.jpg" server="18.179.138.137" local="132981767530385926" remote="132913353600000000" Dst="0" />
<file name="spot_16.jpg" server="18.179.138.137" local="132981767530623551" remote="132913353600000000" Dst="0" />
<file name="works.png" server="18.179.138.137" local="132981767531853786" remote="132913353600000000" Dst="0" />
</dwsync>